poetry_dockerize_plugin/__init__.py
poetry_dockerize_plugin/builder.py
poetry_dockerize_plugin/plugin.py
poetry_dockerize_plugin-1.3.1.dist-info/LICENSE
poetry_dockerize_plugin-1.3.1.dist-info/METADATA
poetry_dockerize_plugin-1.3.1.dist-info/WHEEL
poetry_dockerize_plugin-1.3.1.dist-info/entry_points.txt
poetry_dockerize_plugin-1.3.1.dist-info/RECORD
