Metadata-Version: 2.1
Name: poetry-dockerize-plugin
Version: 1.3.1
Summary: Poetry application to Docker, automatically.
Home-page: https://github.com/nicoloboschi/poetry-dockerize-plugin
License: MIT
Keywords: poetry,packaging,docker
Author: Nicolò Boschi
Author-email: boschi1997@gmail.com
Requires-Python: >=3.9,<4.0
Classifier: Intended Audience :: Developers
Classifier: Intended Audience :: Information Technology
Classifier: Intended Audience :: System Administrators
Classifier: License :: OSI Approved :: MIT License
Classifier: Operating System :: OS Independent
Classifier: Programming Language :: Python
Classifier: Programming Language :: Python :: 3
Classifier: Programming Language :: Python :: 3.9
Classifier: Programming Language :: Python :: 3.10
Classifier: Programming Language :: Python :: 3.11
Classifier: Programming Language :: Python :: 3.12
Classifier: Programming Language :: Python :: 3 :: Only
Classifier: Programming Language :: Python :: 3.7
Classifier: Programming Language :: Python :: 3.8
Classifier: Topic :: Software Development
Classifier: Topic :: Software Development :: Libraries
Classifier: Topic :: Software Development :: Libraries :: Application Frameworks
Classifier: Topic :: Software Development :: Libraries :: Python Modules
Classifier: Topic :: Software Development :: Version Control :: Git
Classifier: Topic :: System :: Archiving :: Packaging
Classifier: Topic :: System :: Installation/Setup
Classifier: Topic :: System :: Software Distribution
Requires-Dist: docker (>=7.1.0,<8.0.0)
Requires-Dist: poetry (>=1.7.1,<2.0.0)
Requires-Dist: poetry-core (>=1.8.1,<2.0.0)
Requires-Dist: python-dotenv (>=1.0.1,<2.0.0)
Requires-Dist: requests (>=2.32.2,<3.0.0)
Project-URL: Documentation, https://github.com/nicoloboschi/poetry-dockerize-plugin
Project-URL: Repository, https://github.com/nicoloboschi/poetry-dockerize-plugin
